dgplib/__init__.py
dgplib/etc.py
dgplib/time_utils.py
dgplib/timesync.py
dgplib/ingest/__init__.py
dgplib/ingest/gravity.py
dgplib/ingest/trajectory.py
dgplib/transform/__init__.py
dgplib/transform/derivatives.py
dgplib/transform/filters.py
dgplib/transform/graph.py
dgplib/transform/gravity.py
dgplib/transform/transform.py
dgplib/transform/transform_graphs.py
lib/__init__.py
lib/etc.py
lib/time_utils.py
lib/timesync.py
lib/ingest/__init__.py
lib/ingest/gravity.py
lib/ingest/trajectory.py
lib/transform/__init__.py
lib/transform/derivatives.py
lib/transform/filters.py
lib/transform/graph.py
lib/transform/gravity.py
lib/transform/transform.py
lib/transform/transform_graphs.py
dgp_lib-1.0.0b2.dist-info/METADATA
dgp_lib-1.0.0b2.dist-info/WHEEL
dgp_lib-1.0.0b2.dist-info/top_level.txt
dgp_lib-1.0.0b2.dist-info/RECORD
